test/__init__.py
test/test_visualise_pattern.py
visualise_spacy_pattern/__init__.py
visualise_spacy_pattern/util.py
visualise_spacy_pattern/visualise_spacy_pattern.py
visualise_spacy_pattern-0.0.3.dist-info/LICENSE
visualise_spacy_pattern-0.0.3.dist-info/METADATA
visualise_spacy_pattern-0.0.3.dist-info/WHEEL
visualise_spacy_pattern-0.0.3.dist-info/top_level.txt
visualise_spacy_pattern-0.0.3.dist-info/RECORD
