Metadata-Version: 2.1
Name: visualise-spacy-pattern
Version: 0.0.3
Summary: Visualise spacy dependency patterns
Home-page: https://github.com/cyclecycle/visualise-spacy-pattern
Author: Nicholas Morley
Author-email: nick.morley111@gmail.com
License: UNKNOWN
Platform: UNKNOWN
Classifier: Programming Language :: Python :: 3
Classifier: License :: OSI Approved :: MIT License
Classifier: Operating System :: OS Independent
Requires-Dist: atomicwrites (==1.3.0)
Requires-Dist: attrs (==19.1.0)
Requires-Dist: importlib-metadata (==0.18)
Requires-Dist: more-itertools (==7.0.0)
Requires-Dist: packaging (==19.0)
Requires-Dist: pluggy (==0.12.0)
Requires-Dist: py (==1.8.0)
Requires-Dist: pydot (==1.4.1)
Requires-Dist: pyparsing (==2.4.0)
Requires-Dist: pytest (==4.6.3)
Requires-Dist: six (==1.12.0)
Requires-Dist: wcwidth (==0.1.7)
Requires-Dist: zipp (==0.5.1)
